<?xml version="1.0" encoding="utf-8"?>
<Defs>
  <ThingDef>
    <defName>SD_Demo_DroneEntity</defName>
    <label>SD_Demo_DroneEntity</label>
    <description>SD_Demo_DroneEntity_description</description>
    <category>Item</category>
    <graphicData>
      <texPath>StellarisDaughter/Things/Drone/SD_DroneEntity</texPath>
      <graphicClass>Graphic_Single</graphicClass>
      <shaderType>Transparent</shaderType>
      <drawSize>1.5</drawSize>
    </graphicData>
    <thingClass>StellarisDaughter.SD_DroneEntity</thingClass>
    <modExtensions>
      <li Class="StellarisDaughter.ModExtension_SD_ShootWithOffset">
        <offsets>
          <li>(-0.18,0.14)</li>
          <li>(0.18,0.14)</li>
          <li>(-0.18,-0.02)</li>
          <li>(0.18,-0.02)</li>
        </offsets>
      </li>
    </modExtensions>
    <thingCategories Inherit="False" />
    <tradeability>None</tradeability>
    <selectable>false</selectable>
    <tickerType>Normal</tickerType>
    <statBases>
      <Mass>0.1</Mass>
      <MaxHitPoints>500</MaxHitPoints>
      <Flammability>0</Flammability>
    </statBases>
  </ThingDef>
  <ThingDef ParentName="BuildingBase">
    <defName>WULA_Fake_Mothership_Beacon_Building</defName>
    <label>帝国母舰信标</label>
    <description>111</description>
    <thingClass>Building</thingClass>
    <preventDroppingThingsOn>true</preventDroppingThingsOn>
    <altitudeLayer>Building</altitudeLayer>
    <pathCost>50</pathCost>
    <blockWind>true</blockWind>
    <passability>PassThroughOnly</passability>
    <fillPercent>1</fillPercent>
    <size>(1,1)</size>
    <drawHighlight>true</drawHighlight>
    <highlightColor>(0.56, 0.62, 0.9)</highlightColor>
    <graphicData>
      <texPath>StellarisDaughter/Things/SD_Empty</texPath>
      <graphicClass>Graphic_Single</graphicClass>
      <shaderType>TransparentPostLight</shaderType>
      <drawSize>(1,1)</drawSize>
      <color>(195,195,195,255)</color>
    </graphicData>
    <statBases>
      <MaxHitPoints>600</MaxHitPoints>
      <Flammability>0.5</Flammability>
      <WorkToBuild>36000</WorkToBuild>
      <Mass>125</Mass>
      <Comfort>0.65</Comfort>
    </statBases>
    <tickerType>Normal</tickerType>
    <canOverlapZones>true</canOverlapZones>
    <rotatable>true</rotatable>
    <hasInteractionCell>false</hasInteractionCell>
    <defaultPlacingRot>North</defaultPlacingRot>
    <selectable>true</selectable>
    <terrainAffordanceNeeded>Light</terrainAffordanceNeeded>
    <soundImpactDefault>BulletImpact_Metal</soundImpactDefault>
    <preventSkyfallersLandingOn>true</preventSkyfallersLandingOn>
    <drawerType>RealtimeOnly</drawerType>
    <repairEffect>ConstructMetal</repairEffect>
    <forceDebugSpawnable>true</forceDebugSpawnable>
    <building>
      <expandHomeArea>false</expandHomeArea>
      <destroySound>BuildingDestroyed_Metal_Big</destroySound>
      <paintable>true</paintable>
      <isInert>true</isInert>
    </building>
    <comps>
      <li Class="StellarisDaughter.CompProperties_FactionSetter">
        <usePlayerFactionIfNull>true</usePlayerFactionIfNull>
        <overrideExistingFaction>false</overrideExistingFaction>
      </li>
      <li Class="StellarisDaughter.CompProperties_AircraftHangar">
        <aircraftDef>WULA_MotherShip_Entity</aircraftDef>
        <aircraftCount>1</aircraftCount>
        <skyfallerLeaving></skyfallerLeaving>
        <autoLaunchEnabled>true</autoLaunchEnabled>
        <autoLaunchDelayTicks>1</autoLaunchDelayTicks>
        <autoLaunchOnConstruction>true</autoLaunchOnConstruction>
        <autoLaunchOnPowerOn>false</autoLaunchOnPowerOn>
      </li>
    </comps>
  </ThingDef>
  <ThingDef>
    <defName>WULA_MotherShip_Entity</defName>
    <label>帝国母舰</label>
    <description>什么？这是个记录数量用的thingdef，你不应该在任何场合下看到这个。</description>
    <thingClass>Thing</thingClass>
  </ThingDef>
</Defs>
